pyrigi/__init__.py
pyrigi/_utils/__init__.py
pyrigi/_utils/_conversion.py
pyrigi/_utils/_doc.py
pyrigi/_utils/_input_check.py
pyrigi/_utils/_zero_check.py
pyrigi/_utils/linear_algebra.py
pyrigi/_utils/repetable_iterator.py
pyrigi/_utils/union_find.py
pyrigi/data_type.py
pyrigi/exception.py
pyrigi/framework/__init__.py
pyrigi/framework/_export/__init__.py
pyrigi/framework/_export/export.py
pyrigi/framework/_general.py
pyrigi/framework/_plot/__init__.py
pyrigi/framework/_plot/plot.py
pyrigi/framework/_rigidity/__init__.py
pyrigi/framework/_rigidity/infinitesimal.py
pyrigi/framework/_rigidity/matroidal.py
pyrigi/framework/_rigidity/redundant.py
pyrigi/framework/_rigidity/second_order.py
pyrigi/framework/_rigidity/stress.py
pyrigi/framework/_transformations/transformations.py
pyrigi/framework/base.py
pyrigi/framework/conftest.py
pyrigi/framework/framework.py
pyrigi/frameworkDB.py
pyrigi/graph/__init__.py
pyrigi/graph/_constructions/constructions.py
pyrigi/graph/_constructions/extensions.py
pyrigi/graph/_export/__init__.py
pyrigi/graph/_export/export.py
pyrigi/graph/_flexibility/__init__.py
pyrigi/graph/_flexibility/nac/__init__.py
pyrigi/graph/_flexibility/nac/algorithms.py
pyrigi/graph/_flexibility/nac/check.py
pyrigi/graph/_flexibility/nac/core.py
pyrigi/graph/_flexibility/nac/cycle_detection.py
pyrigi/graph/_flexibility/nac/facade.py
pyrigi/graph/_flexibility/nac/mono_classes.py
pyrigi/graph/_flexibility/nac/search.py
pyrigi/graph/_flexibility/nac/strategies.py
pyrigi/graph/_general.py
pyrigi/graph/_other/apex.py
pyrigi/graph/_other/separating_set.py
pyrigi/graph/_rigidity/generic.py
pyrigi/graph/_rigidity/global_.py
pyrigi/graph/_rigidity/matroidal.py
pyrigi/graph/_rigidity/redundant.py
pyrigi/graph/_sparsity/_pebble_digraph.py
pyrigi/graph/_sparsity/sparsity.py
pyrigi/graph/_utils/_input_check.py
pyrigi/graph/_utils/utils.py
pyrigi/graph/conftest.py
pyrigi/graph/graph.py
pyrigi/graphDB.py
pyrigi/graph_drawer/__init__.py
pyrigi/graph_drawer/graph_drawer.py
pyrigi-1.1.1.dist-info/LICENSE
pyrigi-1.1.1.dist-info/METADATA
pyrigi-1.1.1.dist-info/WHEEL
pyrigi-1.1.1.dist-info/RECORD
