Metadata-Version: 2.3
Name: pyrigi
Version: 1.1.1
Summary: Python package concerning the rigidity and flexibility of bar-and-joint frameworks.
License: MIT
Author: The PyRigi Developers
Maintainer: Matteo Gallet
Maintainer-email: matteo.gallet@units.it
Requires-Python: >=3.11
Classifier: License :: OSI Approved :: MIT License
Classifier: Operating System :: OS Independent
Classifier: Programming Language :: Python :: 3
Classifier: Programming Language :: Python :: 3.11
Classifier: Programming Language :: Python :: 3.12
Classifier: Programming Language :: Python :: 3.13
Provides-Extra: meshing
Provides-Extra: realization-counting
Requires-Dist: contourpy (>=1.3.1,<2.0.0)
Requires-Dist: distinctipy (>=1.3.4,<2.0.0)
Requires-Dist: ipycanvas (>=0.13.3,<0.14.0)
Requires-Dist: ipyevents (>=2.0.2,<3.0.0)
Requires-Dist: ipympl (>=0.9.6,<0.10.0)
Requires-Dist: ipython (>=8.32.0,<9.0.0)
Requires-Dist: ipywidgets (>=8.1.5,<9.0.0)
Requires-Dist: lnumber ; extra == "realization-counting"
Requires-Dist: manifold3d ; extra == "meshing"
Requires-Dist: matplotlib (>=3.10.0,<4.0.0)
Requires-Dist: networkx (>=3.4.2,<4.0.0)
Requires-Dist: numpy (>=2.2.3,<3.0.0)
Requires-Dist: sympy (>=1.13.3,<2.0.0)
Requires-Dist: trimesh ; extra == "meshing"
Project-URL: Documentation, https://pyrigi.github.io/PyRigi/
Project-URL: Homepage, https://pyrigi.github.io/PyRigi/
Project-URL: Issues, https://github.com/PyRigi/PyRigi/issues
Project-URL: Repository, https://github.com/PyRigi/PyRigi/
